redrock/__init__.py
redrock/_version.py
redrock/archetypes.py
redrock/constants.py
redrock/fitz.py
redrock/igm.py
redrock/plotspec.py
redrock/priors.py
redrock/rebin.py
redrock/results.py
redrock/targets.py
redrock/templates.py
redrock/utils.py
redrock/zfind.py
redrock/zscan.py
redrock/zwarning.py
redrock/data/DLAcoeff.txt
redrock/data/LAFcoeff.txt
redrock/external/__init__.py
redrock/external/boss.py
redrock/external/desi.py
redrock/test/__init__.py
redrock/test/test_archetypes.py
redrock/test/test_igm.py
redrock/test/test_io.py
redrock/test/test_rebin.py
redrock/test/test_templates.py
redrock/test/test_top_level.py
redrock/test/test_utils.py
redrock/test/test_zfind.py
redrock/test/test_zscan.py
redrock/test/util.py
redrock/test/data/README
redrock/test/data/redrock-test.fits
redrock/test/data/rrarchetype-galaxy-test.fits
redrock/test/data/rrdetails-test.h5
redrock-0.21.0.data/scripts/install_redrock_templates
redrock-0.21.0.data/scripts/rrboss
redrock-0.21.0.data/scripts/rrboss_mpi
redrock-0.21.0.data/scripts/rrconvertSDSStemplates
redrock-0.21.0.data/scripts/rrdesi
redrock-0.21.0.data/scripts/rrdesi_mpi
redrock-0.21.0.data/scripts/rrgaltemplate
redrock-0.21.0.data/scripts/rrplot
redrock-0.21.0.data/scripts/rrqsotemplate
redrock-0.21.0.data/scripts/rrspeedtest
redrock-0.21.0.data/scripts/rrstartemplate
redrock-0.21.0.data/scripts/rrstarwdtemplate
redrock-0.21.0.data/scripts/wrap-redrock
redrock-0.21.0.dist-info/licenses/LICENSE.rst
redrock-0.21.0.dist-info/METADATA
redrock-0.21.0.dist-info/WHEEL
redrock-0.21.0.dist-info/top_level.txt
redrock-0.21.0.dist-info/zip-safe
redrock-0.21.0.dist-info/RECORD
