Metadata-Version: 2.4
Name: redrock
Version: 0.21.0
Summary: Redrock redshift fitter
Home-page: https://github.com/desihub/redrock
Author: DESI Collaboration
Author-email: desi-data@desi.lbl.gov
License: BSD-3-Clause
Classifier: Development Status :: 5 - Production/Stable
Classifier: Environment :: Console
Classifier: Intended Audience :: Science/Research
Classifier: Operating System :: OS Independent
Classifier: Programming Language :: Python :: 3
Classifier: Topic :: Scientific/Engineering :: Astronomy
Requires-Python: >=3.10
License-File: LICENSE.rst
Requires-Dist: astropy
Requires-Dist: scipy
Requires-Dist: h5py
Requires-Dist: numba
Requires-Dist: fitsio
Provides-Extra: test
Requires-Dist: pytest; extra == "test"
Provides-Extra: coverage
Requires-Dist: pytest-cov; extra == "coverage"
Requires-Dist: coveralls; extra == "coverage"
Provides-Extra: doc
Requires-Dist: Sphinx; extra == "doc"
Requires-Dist: sphinx-rtd-theme; extra == "doc"
Provides-Extra: desi
Requires-Dist: desiutil; extra == "desi"
Requires-Dist: desispec; extra == "desi"
Dynamic: license-file
